README.txt
bootstrap.py
buildout.cfg
setup.py
gocept/__init__.py
gocept.nginx.egg-info/PKG-INFO
gocept.nginx.egg-info/SOURCES.txt
gocept.nginx.egg-info/dependency_links.txt
gocept.nginx.egg-info/entry_points.txt
gocept.nginx.egg-info/namespace_packages.txt
gocept.nginx.egg-info/not-zip-safe
gocept.nginx.egg-info/requires.txt
gocept.nginx.egg-info/top_level.txt
gocept/nginx/README.txt
gocept/nginx/__init__.py
gocept/nginx/nginxctl.in
gocept/nginx/recipe.py
gocept/nginx/tests.py