Metadata-Version: 1.0
Name: gocept.nginx
Version: 0.9.3
Summary: zc.buildout recipe for configuring an nginx server
Home-page: UNKNOWN
Author: Christian Theune
Author-email: ct@gocept.com
License: ZPL 2.1
Keywords: zope3 buildout nginx
Platform: UNKNOWN
Classifier: Framework :: Buildout
